grappl_node/__init__.py
grappl_node/main.py
grappl_node/core/__init__.py
grappl_node/core/base_input.py
grappl_node/core/base_node.py
grappl_node/core/base_output.py
grappl_node/core/event.py
grappl_node/core/inputs/__init__.py
grappl_node/core/inputs/on_demand_counter_input.py
grappl_node/core/outputs/__init__.py
grappl_node/core/outputs/null_output.py
grappl_node/run/__init__.py
grappl_node/run/cli.py
grappl_node/run/creator.py
grappl_node/run/entrypoint.py
grappl_node/run/loader.py
grappl_node/run/cli_configurations/__init__.py
grappl_node/run/cli_configurations/base_configuration.py
grappl_node/run/cli_configurations/cli_configuration.py
grappl_node/run/cli_configurations/env_vars_configuration.py
grappl_node/run/cli_configurations/json_configuration.py
grappl_node/run/cli_configurations/utils.py
grappl_node-0.1.0.dist-info/METADATA
grappl_node-0.1.0.dist-info/WHEEL
grappl_node-0.1.0.dist-info/entry_points.txt
grappl_node-0.1.0.dist-info/top_level.txt
grappl_node-0.1.0.dist-info/RECORD
