Metadata-Version: 2.1
Name: grappl-node
Version: 0.1.0
Summary: Writing nodes for the grappl framework
Home-page: https://github.com/Tipshim/grappl-node
Author: jonirap
Author-email: joni.rapoport@gmail.com
License: UNKNOWN
Platform: UNKNOWN
Classifier: Programming Language :: Python :: 3
Classifier: License :: OSI Approved :: MIT License
Classifier: Operating System :: OS Independent
Requires-Python: >=3.8.2
Requires-Dist: Click
Requires-Dist: decorator
Requires-Dist: ipdb
Requires-Dist: itertools
Requires-Dist: json
Requires-Dist: yaml
